__init__.py
use_factory.py
use_factory-0.2.dist-info/LICENSE
use_factory-0.2.dist-info/METADATA
use_factory-0.2.dist-info/WHEEL
use_factory-0.2.dist-info/top_level.txt
use_factory-0.2.dist-info/RECORD
